LICENSE
README.md
setup.py
GoogleSearch/__init__.py
GoogleSearch/search.py
google_reverse_search.egg-info/PKG-INFO
google_reverse_search.egg-info/SOURCES.txt
google_reverse_search.egg-info/dependency_links.txt
google_reverse_search.egg-info/requires.txt
google_reverse_search.egg-info/top_level.txt