Metadata-Version: 2.1
Name: google-reverse-search
Version: 0.1.3
Summary: Simple python library to reverse search any image via file or url
Home-page: https://github.com/Black-Bulls-Bots/google-reverse-search
Author: Joker Hacker
Author-email: jokerhacker.6521@protonmail.com
License: License :: OSI Approved :: GNU Lesser General Public License v3 (LGPLv3)
Project-URL: Discussion, https://t.me/blackbulls_support
Platform: UNKNOWN
Requires-Python: >=3.8
License-File: LICENSE
